pytest_concurrent/__init__.py
pytest_concurrent/plugin.py
pytest_concurrent/modes/__init__.py
pytest_concurrent/modes/asyncnet.py
pytest_concurrent/modes/base.py
pytest_concurrent/modes/mproc.py
pytest_concurrent/modes/mthread.py
pytest_concurrent/modes/traditional.py
pytest_concurrent-0.2.1.dist-info/LICENSE
pytest_concurrent-0.2.1.dist-info/METADATA
pytest_concurrent-0.2.1.dist-info/WHEEL
pytest_concurrent-0.2.1.dist-info/entry_points.txt
pytest_concurrent-0.2.1.dist-info/top_level.txt
pytest_concurrent-0.2.1.dist-info/RECORD
