Metadata-Version: 2.1
Name: pytest-concurrent
Version: 0.2.1
Summary: Concurrently execute test cases with multithread, multiprocess and gevent
Home-page: https://github.com/reverbc/pytest-concurrent
Author: James Wang, Reverb Chu
Author-email: jamesw96@uw.edu, reverbc@me.com
Maintainer: James Wang, Reverb Chu
Maintainer-email: jamesw96@uw.edu, reverbc@me.com
License: MIT
Platform: UNKNOWN
Classifier: Development Status :: 4 - Beta
Classifier: Framework :: Pytest
Classifier: Intended Audience :: Developers
Classifier: Topic :: Software Development :: Testing
Classifier: Programming Language :: Python
Classifier: Programming Language :: Python :: 2
Classifier: Programming Language :: Python :: 2.7
Classifier: Programming Language :: Python :: 3
Classifier: Programming Language :: Python :: 3.4
Classifier: Programming Language :: Python :: 3.5
Classifier: Programming Language :: Python :: 3.6
Classifier: Programming Language :: Python :: 3.7
Classifier: Programming Language :: Python :: Implementation :: CPython
Classifier: Operating System :: OS Independent
Classifier: License :: OSI Approved :: MIT License
Requires-Dist: pytest (>=3.1.1)
Requires-Dist: psutil (>=5.2.2)
Requires-Dist: futures ; python_version < "3.0"
